LICENSE
README.rst
setup.py
pyshtrih/__init__.py
pyshtrih/commands.py
pyshtrih/compat.py
pyshtrih/device.py
pyshtrih/excepts.py
pyshtrih/fd.py
pyshtrih/misc.py
pyshtrih/protocol.py
pyshtrih/utils.py
pyshtrih.egg-info/PKG-INFO
pyshtrih.egg-info/SOURCES.txt
pyshtrih.egg-info/dependency_links.txt
pyshtrih.egg-info/not-zip-safe
pyshtrih.egg-info/requires.txt
pyshtrih.egg-info/top_level.txt
pyshtrih/handlers/__init__.py
pyshtrih/handlers/commands.py
pyshtrih/handlers/functions.py