Metadata-Version: 2.1
Name: pyshtrih
Version: 2.0.6
Summary: Реализация драйвера семейства ККМ "Штрих" на Python.
Home-page: https://github.com/oleg-golovanov/pyshtrih
Author: Oleg Golovanov
Author-email: golovanov.ov@gmail.com
License: MIT
Platform: any
Classifier: Development Status :: 5 - Production/Stable
Classifier: Intended Audience :: Developers
Classifier: Operating System :: OS Independent
Classifier: Programming Language :: Python :: 2.7
Classifier: Programming Language :: Python :: 3.3
Classifier: Programming Language :: Python :: 3.4
Classifier: Programming Language :: Python :: 3.5
Classifier: Programming Language :: Python :: 3.6
Classifier: Programming Language :: Python :: Implementation :: CPython
Classifier: Topic :: Software Development :: Libraries :: Python Modules
Classifier: Topic :: Office/Business :: Financial :: Accounting
Classifier: Topic :: Office/Business :: Financial :: Point-Of-Sale
Classifier: Topic :: System :: Hardware :: Hardware Drivers
Classifier: Natural Language :: Russian
License-File: LICENSE
